midfile/__init__.py
midfile/cli.py
midfile/cloud.py
midfile/config.py
midfile/db.py
midfile/midfile.yml
midfile-0.1.6.dist-info/METADATA
midfile-0.1.6.dist-info/WHEEL
midfile-0.1.6.dist-info/entry_points.txt
midfile-0.1.6.dist-info/RECORD
