Metadata-Version: 2.4
Name: midfile
Version: 0.1.6
Summary: 中间文件数据库管理系统
Author: Yuan Zan
Author-email: yfinddream@gmail.com
Requires-Python: >=3.8,<4.0
Classifier: Programming Language :: Python :: 3
Classifier: Programming Language :: Python :: 3.8
Classifier: Programming Language :: Python :: 3.9
Classifier: Programming Language :: Python :: 3.10
Classifier: Programming Language :: Python :: 3.11
Classifier: Programming Language :: Python :: 3.12
Classifier: Programming Language :: Python :: 3.13
Classifier: Programming Language :: Python :: 3.14
Requires-Dist: boto3 (>=1.26.0,<2.0.0)
Requires-Dist: click (>=8.0.0,<9.0.0)
Requires-Dist: pandas (>=1.3.0,<2.0.0)
Requires-Dist: pyyaml (>=6.0,<7.0)
